[{"id":"RG001","no":1,"name":"Kanto"},{"id":"RG002","no":2,"name":"Johto"},{"id":"RG003","no":3,"name":"Hoenn"},{"id":"RG004","no":4,"name":"Sinnoh"},{"id":"RG005","no":5,"name":"Unima"},{"id":"RG006","no":6,"name":"Kalos"},{"id":"RG007","no":7,"name":"Alola"},{"id":"RG008","no":8,"name":"Pokémon GO"},{"id":"RG009","no":9,"name":"Kanto"},{"id":"RG010","no":10,"name":"Johto"},{"id":"RG011","no":11,"name":"Kanto"},{"id":"RG012","no":12,"name":"Galar"},{"id":"RG013","no":13,"name":"Pokémon HOME"},{"id":"RG014","no":14,"name":"Terra Lontana"},{"id":"RG015","no":15,"name":"Hisui"},{"id":"RG016","no":16,"name":""},{"id":"RG017","no":17,"name":"Paldea"},{"id":"RG018","no":18,"name":"Kalos"}]