[{"id":888,"form":0},{"id":717,"form":0},{"id":382,"form":0},{"id":802,"form":0},{"id":890,"form":0},{"id":898,"form":2},{"id":383,"form":0},{"id":645,"form":1},{"id":483,"form":0},{"id":800,"form":1},{"id":250,"form":0},{"id":716,"form":0},{"id":809,"form":0},{"id":894,"form":0},{"id":721,"form":0},{"id":898,"form":1},{"id":807,"form":0},{"id":644,"form":0},{"id":484,"form":0},{"id":150,"form":0},{"id":889,"form":0},{"id":145,"form":0},{"id":646,"form":1},{"id":718,"form":3},{"id":892,"form":0},{"id":249,"form":0},{"id":892,"form":1},{"id":643,"form":0},{"id":384,"form":0},{"id":801,"form":0},{"id":646,"form":2},{"id":788,"form":0},{"id":649,"form":0},{"id":151,"form":0},{"id":245,"form":0},{"id":488,"form":0},{"id":494,"form":0},{"id":146,"form":1},{"id":642,"form":0},{"id":795,"form":0},{"id":385,"form":0},{"id":785,"form":0},{"id":485,"form":0},{"id":792,"form":0},{"id":480,"form":0},{"id":791,"form":0},{"id":797,"form":0},{"id":487,"form":1},{"id":719,"form":0},{"id":244,"form":0},{"id":798,"form":0},{"id":793,"form":0},{"id":487,"form":0},{"id":145,"form":1},{"id":647,"form":0},{"id":786,"form":0},{"id":641,"form":0},{"id":806,"form":0},{"id":800,"form":2},{"id":380,"form":0},{"id":251,"form":0},{"id":895,"form":0},{"id":381,"form":0},{"id":144,"form":1},{"id":804,"form":0},{"id":645,"form":0},{"id":718,"form":2},{"id":896,"form":0},{"id":146,"form":0},{"id":805,"form":0},{"id":486,"form":0},{"id":377,"form":0},{"id":378,"form":0},{"id":799,"form":0},{"id":379,"form":0},{"id":243,"form":0},{"id":642,"form":1},{"id":794,"form":0},{"id":144,"form":0},{"id":772,"form":0},{"id":787,"form":0},{"id":773,"form":0},{"id":796,"form":0},{"id":639,"form":0},{"id":897,"form":0},{"id":638,"form":0},{"id":482,"form":0},{"id":646,"form":0},{"id":640,"form":0},{"id":800,"form":0},{"id":481,"form":0},{"id":773,"form":16},{"id":641,"form":1},{"id":718,"form":0},{"id":773,"form":6},{"id":773,"form":17},{"id":803,"form":0},{"id":891,"form":0},{"id":898,"form":0},{"id":789,"form":0},{"id":773,"form":10},{"id":773,"form":4},{"id":773,"form":11},{"id":773,"form":7},{"id":773,"form":15},{"id":773,"form":3},{"id":808,"form":0},{"id":773,"form":14},{"id":718,"form":1},{"id":773,"form":12},{"id":790,"form":0},{"id":773,"form":8},{"id":773,"form":9},{"id":773,"form":2},{"id":773,"form":5}]